const/__init__.py
const/const.py
constpy-0.2.0.dist-info/AUTHORS.rst
constpy-0.2.0.dist-info/LICENSE
constpy-0.2.0.dist-info/METADATA
constpy-0.2.0.dist-info/WHEEL
constpy-0.2.0.dist-info/top_level.txt
constpy-0.2.0.dist-info/RECORD
