Metadata-Version: 2.1
Name: constpy
Version: 0.2.0
Summary: Define constants for your project
Home-page: https://bitbucket.org/htv2013/constpy/
Author: Hai Vu
Author-email: haivu2004@gmail.com
License: MIT license
Keywords: constpy
Platform: UNKNOWN
Classifier: Development Status :: 2 - Pre-Alpha
Classifier: Intended Audience :: Developers
Classifier: License :: OSI Approved :: MIT License
Classifier: Natural Language :: English
Classifier: Programming Language :: Python :: 3
Classifier: Programming Language :: Python :: 3.5
Classifier: Programming Language :: Python :: 3.6
Classifier: Programming Language :: Python :: 3.7
Classifier: Programming Language :: Python :: 3.8
Requires-Python: >=3.5
